strie/__init__.py
strie/cmds/__init__.py
strie/cmds/arg.py
strie/cmds/get.py
strie/cmds/init.py
strie/cmds/list.py
strie/cmds/pop.py
strie/cmds/set.py
strie/store/__init__.py
strie/store/dfile.py
strie/store/mfile.py
strie/store/nfile.py
strie/trie/__init__.py
strie/trie/ctree.py
strie/trie/htree.py
strie/trie/rtree.py
strie/utils/__init__.py
strie/utils/attribute.py
strie/utils/vkey.py
strie-0.2.dist-info/LICENSE
strie-0.2.dist-info/METADATA
strie-0.2.dist-info/WHEEL
strie-0.2.dist-info/entry_points.txt
strie-0.2.dist-info/top_level.txt
strie-0.2.dist-info/zip-safe
strie-0.2.dist-info/RECORD
