Metadata-Version: 2.1
Name: strie
Version: 0.2
Summary: Storage string trie.
Home-page: https://github.com/bondbox/strie/
Author: Mingzhe Zou
Author-email: zoumingzhe@outlook.com
License: MIT
Project-URL: Source Code, https://github.com/bondbox/strie/
Project-URL: Bug Tracker, https://github.com/bondbox/strie/issues
Project-URL: Documentation, https://github.com/bondbox/strie/
Keywords: trie,string
Platform: any
Classifier: Programming Language :: Python
Classifier: Programming Language :: Python :: 3
Requires-Python: >=3.8
License-File: LICENSE
Requires-Dist: xarg-python >=1.2.1
Requires-Dist: cachetools
